actory/__init__.py
actory/client.py
actory/models.py
actory-0.1.5.dist-info/METADATA
actory-0.1.5.dist-info/WHEEL
actory-0.1.5.dist-info/top_level.txt
actory-0.1.5.dist-info/RECORD
