Metadata-Version: 2.4
Name: actory
Version: 0.1.5
Summary: Official Python SDK for the Actory Agent Commerce Protocol (ACP) API
Author-email: Actory <hello@actory.ai>
License: MIT
Project-URL: Homepage, https://actory.ai
Project-URL: Documentation, https://actory.ai/docs
Project-URL: Repository, https://github.com/actory-ai/actory-python
Keywords: actory,acp,ai,agent,commerce,api,sdk
Classifier: Development Status :: 3 - Alpha
Classifier: Intended Audience :: Developers
Classifier: License :: OSI Approved :: MIT License
Classifier: Programming Language :: Python :: 3
Classifier: Programming Language :: Python :: 3.8
Classifier: Programming Language :: Python :: 3.9
Classifier: Programming Language :: Python :: 3.10
Classifier: Programming Language :: Python :: 3.11
Classifier: Programming Language :: Python :: 3.12
Requires-Python: >=3.8
Requires-Dist: requests>=2.25.0
Provides-Extra: dev
Requires-Dist: pytest>=7.0; extra == "dev"
Requires-Dist: pytest-cov>=4.0; extra == "dev"
